coveo_ref/__init__.py
coveo_ref/exceptions.py
coveo_ref/py.typed
coveo_ref-2.0.1.dist-info/METADATA
coveo_ref-2.0.1.dist-info/WHEEL
coveo_ref-2.0.1.dist-info/RECORD
